[
  {
    "profile": "3",
    "0": "3",
    "beschreibung": "Profil3: Auu00dfenflu00e4che und Innenflu00e4che standard gewu00f6lbt. Ecken gerundet.",
    "1": "Profil3: Auu00dfenflu00e4che und Innenflu00e4che standard gewu00f6lbt. Ecken gerundet.",
    "333er_gelbgold": "3.9312",
    "2": "3.9312",
    "333er_rotgold": "3.972",
    "3": "3.972",
    "333er_rosu00e9gold": "3.972",
    "4": "3.972",
    "333er_weiu00dfgold": "4.5722",
    "5": "4.5722",
    "375er_gelbgold": "4.0386",
    "6": "4.0386",
    "375er_rotgold": "4.1246",
    "7": "4.1246",
    "375er_rosu00e9gold": "4.1246",
    "8": "4.1246",
    "375er_weiu00dfgold": "4.6925",
    "9": "4.6925",
    "585er_gelbgold": "4.7197",
    "10": "4.7197",
    "585er_rotgold": "4.7881",
    "11": "4.7881",
    "585er_rosu00e9gold": "4.943",
    "12": "4.943",
    "585er_weiu00dfgold": "5.2666",
    "13": "5.2666",
    "750er_gelbgold": "5.7186",
    "14": "5.7186",
    "750er_rotgold": "5.5012",
    "15": "5.5012",
    "750er_rosu00e9gold": "5.6189",
    "16": "5.6189",
    "750er_weiu00dfgold": "5.8367",
    "17": "5.8367",
    "585er_palladium": "4.0551",
    "18": "4.0551",
    "950er_palladium": "4.2843",
    "19": "4.2843",
    "600er_platin": "5.0349",
    "20": "5.0349",
    "950er_platin": "7.7469",
    "21": "7.7469"
  }
]
